[{
      "id": 1,
      "image": "../assets/user.svg",
      "fullname": "Admin",
      "username": "Admin",
      "password": "admin",
      "email": "admin@gmail.com",
      "gender": "Male",
      "address": "Surabaya",
      "phone": "0123456789",
      "status": "Admin",
      "order":[]
    },
    {
      "id": 2,
      "image":"../assets/photo.png",
      "fullname": "user",
      "username": "user",
      "password": "123456",
      "email": "user@gmail.com",
      "gender": "Male",
      "address": "Jakarta",
      "phone": "0123456789",
      "status": "Customer",
      "order":[]
    }

  ]